threadit/__init__.py
threadit-1.2.3.dist-info/LICENSE
threadit-1.2.3.dist-info/METADATA
threadit-1.2.3.dist-info/WHEEL
threadit-1.2.3.dist-info/top_level.txt
threadit-1.2.3.dist-info/RECORD
