Metadata-Version: 2.1
Name: threadit
Version: 1.2.3
Summary: Takes the hassle away from threading functions and getting their results
Home-page: https://github.com/AdaptedAS/threadit
Author: Odd Jøren Røland
Author-email: odd@adapted.no
License: MIT
Keywords: threading,threads
Platform: any
Classifier: License :: OSI Approved :: MIT License
Classifier: Natural Language :: English
Classifier: Intended Audience :: Developers
Classifier: Topic :: Software Development :: Libraries
Classifier: Topic :: Software Development :: Libraries :: Python Modules
Classifier: Development Status :: 5 - Production/Stable
Classifier: Programming Language :: Python
Classifier: Programming Language :: Python :: 3
Classifier: Programming Language :: Python :: 3.4
Classifier: Programming Language :: Python :: 3.5
Classifier: Programming Language :: Python :: 3.6
Classifier: Programming Language :: Python :: 3.7
